ragas_examples/__init__.py
ragas_examples/_version.py
ragas_examples/ag_ui_agent_experiments/__init__.py
ragas_examples/ag_ui_agent_experiments/experiments.py
ragas_examples/ag_ui_agent_experiments/test_data/datasets/scientist_biographies.csv
ragas_examples/ag_ui_agent_experiments/test_data/datasets/weather_tool_calls.csv
ragas_examples/agent_evals/__init__.py
ragas_examples/agent_evals/agent.py
ragas_examples/agent_evals/evals.py
ragas_examples/benchmark_llm/__init__.py
ragas_examples/benchmark_llm/evals.py
ragas_examples/benchmark_llm/prompt.py
ragas_examples/benchmark_llm/datasets/discount_benchmark.csv
ragas_examples/improve_rag/__init__.py
ragas_examples/improve_rag/evals.py
ragas_examples/improve_rag/rag.py
ragas_examples/improve_rag/evals/datasets/hf_doc_qa_eval.csv
ragas_examples/judge_alignment/__init__.py
ragas_examples/judge_alignment/evals.py
ragas_examples/llamaIndex_agent_evals/__init__.py
ragas_examples/llamaIndex_agent_evals/evals.py
ragas_examples/llamaIndex_agent_evals/llamaindex_agent.py
ragas_examples/prompt_evals/__init__.py
ragas_examples/prompt_evals/evals.py
ragas_examples/prompt_evals/prompt.py
ragas_examples/rag_eval/__init__.py
ragas_examples/rag_eval/evals.py
ragas_examples/rag_eval/rag.py
ragas_examples/text2sql/__init__.py
ragas_examples/text2sql/analyze_errors.py
ragas_examples/text2sql/data_utils.py
ragas_examples/text2sql/db_utils.py
ragas_examples/text2sql/evals.py
ragas_examples/text2sql/prompt.txt
ragas_examples/text2sql/prompt_v2.txt
ragas_examples/text2sql/prompt_v3.txt
ragas_examples/text2sql/text2sql_agent.py
ragas_examples/text2sql/validate_sql_dataset.py
ragas_examples/text2sql/datasets/booksql_sample.csv
ragas_examples/workflow_eval/__init__.py
ragas_examples/workflow_eval/evals.py
ragas_examples/workflow_eval/workflow.py
ragas_examples-0.4.3.dist-info/licenses/LICENSE
ragas_examples-0.4.3.dist-info/METADATA
ragas_examples-0.4.3.dist-info/WHEEL
ragas_examples-0.4.3.dist-info/entry_points.txt
ragas_examples-0.4.3.dist-info/top_level.txt
ragas_examples-0.4.3.dist-info/RECORD
