Metadata-Version: 2.4
Name: ragas-examples
Version: 0.4.3
Summary: Official examples for the ragas project
Author: Ragas Team
License: Apache-2.0
Project-URL: Homepage, https://github.com/vibrantlabsai/ragas
Project-URL: Documentation, https://docs.ragas.io
Project-URL: Code, https://github.com/vibrantlabsai/ragas
Project-URL: Issues, https://github.com/vibrantlabsai/ragas/issues
Classifier: Development Status :: 4 - Beta
Classifier: Intended Audience :: Developers
Classifier: License :: OSI Approved :: Apache Software License
Classifier: Programming Language :: Python :: 3
Classifier: Programming Language :: Python :: 3.9
Classifier: Programming Language :: Python :: 3.10
Classifier: Programming Language :: Python :: 3.11
Classifier: Programming Language :: Python :: 3.12
Classifier: Topic :: Scientific/Engineering :: Artificial Intelligence
Classifier: Topic :: Software Development :: Libraries :: Python Modules
Requires-Python: >=3.9
License-File: LICENSE
Requires-Dist: ragas
Requires-Dist: openai>=1.0.0
Requires-Dist: pandas
Provides-Extra: gdrive
Requires-Dist: ragas[gdrive]; extra == "gdrive"
Provides-Extra: text2sql
Requires-Dist: huggingface_hub>=0.16.0; extra == "text2sql"
Requires-Dist: datacompy>=0.8.0; extra == "text2sql"
Requires-Dist: python-dotenv>=1.0.0; extra == "text2sql"
Provides-Extra: improverag
Requires-Dist: mlflow>=3.1.4; extra == "improverag"
Requires-Dist: rank_bm25; extra == "improverag"
Requires-Dist: datasets; extra == "improverag"
Requires-Dist: langchain; extra == "improverag"
Requires-Dist: langchain-community; extra == "improverag"
Requires-Dist: tqdm; extra == "improverag"
Requires-Dist: python-dotenv>=1.0.0; extra == "improverag"
Requires-Dist: openai-agents>=0.2.9; extra == "improverag"
Provides-Extra: llamaindex
Requires-Dist: llama-index>=0.10.0; extra == "llamaindex"
Requires-Dist: llama-index-llms-google-genai; extra == "llamaindex"
Requires-Dist: instructor; extra == "llamaindex"
Dynamic: license-file
